seg_lib/dataloaders/__init__.py
seg_lib/dataloaders/data_aug.py
seg_lib/dataloaders/image_ops.py
seg_lib/dataloaders/sam_dataset.py
seg_lib/dataloaders/samus_data_aug.py
seg_lib/dataloaders/seg_dataset.py
seg_lib/eval/__init__.py
seg_lib/eval/fusion.py
seg_lib/eval/metrics.py
seg_lib/eval/outputs.py
seg_lib/eval/plots.py
seg_lib/io/__init__.py
seg_lib/io/files.py
seg_lib/io/image.py
seg_lib/io/labelme.py
seg_lib/losses/__init__.py
seg_lib/losses/combined_losses.py
seg_lib/losses/dice_loss.py
seg_lib/losses/focal_loss.py
seg_lib/losses/selector.py
seg_lib/models/__init__.py
seg_lib/models/cafe_net/PSA.py
seg_lib/models/cafe_net/__init__.py
seg_lib/models/cafe_net/pvt.py
seg_lib/models/cafe_net/pvtv2.py
seg_lib/models/device.py
seg_lib/models/normalizer.py
seg_lib/models/pvt_v2/__init__.py
seg_lib/models/pvt_v2/pvt_v2_backbone.py
seg_lib/models/pvt_v2/pvt_v2_seg.py
seg_lib/models/sam/__init__.py
seg_lib/models/sam/build_sam.py
seg_lib/models/sam/modeling/__init__.py
seg_lib/models/sam/modeling/common.py
seg_lib/models/sam/modeling/image_encoder.py
seg_lib/models/sam/modeling/mask_decoder.py
seg_lib/models/sam/modeling/prompt_encoder.py
seg_lib/models/sam/modeling/sam.py
seg_lib/models/sam/modeling/sam_batch_inf.py
seg_lib/models/sam/modeling/transformer.py
seg_lib/models/sam/predictor.py
seg_lib/models/sam/transforms.py
seg_lib/models/sam_med2d/LICENSE
seg_lib/models/sam_med2d/__init__.py
seg_lib/models/sam_med2d/build_sam_med2d.py
seg_lib/models/sam_med2d/modeling/__init__.py
seg_lib/models/sam_med2d/modeling/common.py
seg_lib/models/sam_med2d/modeling/image_encoder.py
seg_lib/models/sam_med2d/modeling/mask_decoder.py
seg_lib/models/sam_med2d/modeling/prompt_encoder.py
seg_lib/models/sam_med2d/modeling/sam.py
seg_lib/models/sam_med2d/modeling/sam_model.py
seg_lib/models/sam_med2d/modeling/transformer.py
seg_lib/models/sam_med2d/predictor.py
seg_lib/models/samus/LICENSE
seg_lib/models/samus/__init__.py
seg_lib/models/samus/automatic_mask_generator.py
seg_lib-1.0.4.dist-info/LICENSE
seg_lib-1.0.4.dist-info/METADATA
seg_lib-1.0.4.dist-info/WHEEL
seg_lib-1.0.4.dist-info/RECORD
