Metadata-Version: 2.1
Name: seg-lib
Version: 1.0.4
Summary: A library for the development of segmentation models.
Author: Gustavo Zanoni
Author-email: gzf1996@gmail.com
Requires-Python: >=3.10,<4.0
Classifier: Programming Language :: Python :: 3
Classifier: Programming Language :: Python :: 3.10
Classifier: Programming Language :: Python :: 3.11
Classifier: Programming Language :: Python :: 3.12
Requires-Dist: albumentations (<=1.3.1)
Requires-Dist: matplotlib (>=3.8.2)
Requires-Dist: numpy (>=1.26.3)
Requires-Dist: opencv-python (>=4.9.0.80)
Requires-Dist: pandas (>=2.2.0)
Requires-Dist: pyarrow (>=15.0.0)
Requires-Dist: pytest (>=8.3.3)
Requires-Dist: samv2 (>=0.0.4)
Requires-Dist: scikit-learn (>=1.5.2)
Requires-Dist: scipy (>=1.12.0)
Requires-Dist: timm (>=0.9.12)
Requires-Dist: torch (>=2.1.2)
Requires-Dist: torchvision (>=0.16.2)
Requires-Dist: tqdm (>=4.66.1)
Requires-Dist: transformers (>=4.35.2)
